planer_cli/__init__.py
planer_cli/__main__.py
planer_cli/api/__init__.py
planer_cli/api/client.py
planer_cli/api/exceptions.py
planer_cli/api/groups.py
planer_cli/api/planner.py
planer_cli/api/users.py
planer_cli/auth/__init__.py
planer_cli/auth/cache.py
planer_cli/auth/manager.py
planer_cli/cli/__init__.py
planer_cli/cli/buckets.py
planer_cli/cli/common.py
planer_cli/cli/completions.py
planer_cli/cli/config.py
planer_cli/cli/groups.py
planer_cli/cli/main.py
planer_cli/cli/plans.py
planer_cli/cli/tasks.py
planer_cli/cli/users.py
planer_cli/cli/watch.py
planer_cli/config/__init__.py
planer_cli/config/settings.py
planer_cli/models/__init__.py
planer_cli/models/bucket.py
planer_cli/models/group.py
planer_cli/models/plan.py
planer_cli/models/task.py
planer_cli/models/user.py
planer_cli/output/__init__.py
planer_cli/output/formatter.py
planer_cli/output/tables.py
planer_cli-0.2.1.dist-info/METADATA
planer_cli-0.2.1.dist-info/WHEEL
planer_cli-0.2.1.dist-info/entry_points.txt
planer_cli-0.2.1.dist-info/licenses/LICENSE
planer_cli-0.2.1.dist-info/RECORD
