Metadata-Version: 2.4
Name: planer-cli
Version: 0.2.1
Summary: CLI tool for Microsoft Planner - manage plans, tasks, and buckets
Project-URL: Homepage, https://github.com/jvanvinkenroye/planer-cli
Project-URL: Repository, https://github.com/jvanvinkenroye/planer-cli
Project-URL: Issues, https://github.com/jvanvinkenroye/planer-cli/issues
Author-email: Jan Vanvinkenroye <jan@vanvinkenroye.de>
License: MIT
License-File: LICENSE
Keywords: cli,microsoft,planner,productivity,tasks
Classifier: Development Status :: 4 - Beta
Classifier: Environment :: Console
Classifier: Intended Audience :: Developers
Classifier: Intended Audience :: End Users/Desktop
Classifier: License :: OSI Approved :: MIT License
Classifier: Operating System :: OS Independent
Classifier: Programming Language :: Python :: 3
Classifier: Programming Language :: Python :: 3.11
Classifier: Programming Language :: Python :: 3.12
Classifier: Topic :: Office/Business :: Scheduling
Classifier: Topic :: Utilities
Requires-Python: >=3.11
Requires-Dist: click>=8.1.0
Requires-Dist: dateparser>=1.2.2
Requires-Dist: httpx>=0.27.0
Requires-Dist: msal>=1.28.0
Requires-Dist: pydantic-settings>=2.0.0
Requires-Dist: pydantic>=2.0.0
Requires-Dist: python-dateutil>=2.8.0
Requires-Dist: pyyaml>=6.0.3
Requires-Dist: rich>=13.0.0
